pe_accounting_python_objects/__init__.py
pe_accounting_python_objects/user.py
pe_accounting_python_objects-0.0.16.dist-info/METADATA
pe_accounting_python_objects-0.0.16.dist-info/WHEEL
pe_accounting_python_objects-0.0.16.dist-info/top_level.txt
pe_accounting_python_objects-0.0.16.dist-info/RECORD
