Metadata-Version: 2.1
Name: pe-accounting-python-objects
Version: 0.0.16
Summary: API objects for https://www.accounting.pe/sv/
Home-page: https://github.com/najlen/pe-accounting-python-objects
Author: Daniel Nihlén
Author-email: daniel.nihlen@sdnit.se
License: MIT
Platform: UNKNOWN
Classifier: License :: OSI Approved :: MIT License
Classifier: Programming Language :: Python :: 3
Classifier: Programming Language :: Python :: 3.8
Requires-Dist: loguru
Requires-Dist: python-dateutil
Requires-Dist: pe-accounting-python-api
Requires-Dist: pydantic
